{
  "openapi": "3.0.1",
  "info": {
    "title": "Event_Mangement_System_WebTech_Project",
    "version": "1.0"
  },
  "paths": {
    "/auth/Auth/register": {
      "post": {
        "tags": [
          "Auth"
        ],
        "requestBody": {
          "content": {
            "application/json": {
              "schema": {
                "$ref": "#/components/schemas/UserDto"
              }
            },
            "text/json": {
              "schema": {
                "$ref": "#/components/schemas/UserDto"
              }
            },
            "application/*+json": {
              "schema": {
                "$ref": "#/components/schemas/UserDto"
              }
            }
          }
        },
        "responses": {
          "200": {
            "description": "OK"
          }
        }
      }
    },
    "/auth/Auth/login": {
      "post": {
        "tags": [
          "Auth"
        ],
        "requestBody": {
          "content": {
            "application/json": {
              "schema": {
                "$ref": "#/components/schemas/UserDto"
              }
            },
            "text/json": {
              "schema": {
                "$ref": "#/components/schemas/UserDto"
              }
            },
            "application/*+json": {
              "schema": {
                "$ref": "#/components/schemas/UserDto"
              }
            }
          }
        },
        "responses": {
          "200": {
            "description": "OK"
          }
        }
      }
    },
    "/api/Events": {
      "get": {
        "tags": [
          "Events"
        ],
        "responses": {
          "200": {
            "description": "OK"
          }
        }
      },
      "post": {
        "tags": [
          "Events"
        ],
        "requestBody": {
          "content": {
            "application/json": {
              "schema": {
                "$ref": "#/components/schemas/EventDto"
              }
            },
            "text/json": {
              "schema": {
                "$ref": "#/components/schemas/EventDto"
              }
            },
            "application/*+json": {
              "schema": {
                "$ref": "#/components/schemas/EventDto"
              }
            }
          }
        },
        "responses": {
          "200": {
            "description": "OK"
          }
        }
      }
    },
    "/api/Events/{id}": {
      "get": {
        "tags": [
          "Events"
        ],
        "parameters": [
          {
            "name": "id",
            "in": "path",
            "required": true,
            "schema": {
              "type": "integer",
              "format": "int32"
            }
          }
        ],
        "responses": {
          "200": {
            "description": "OK"
          }
        }
      },
      "put": {
        "tags": [
          "Events"
        ],
        "parameters": [
          {
            "name": "id",
            "in": "path",
            "required": true,
            "schema": {
              "type": "integer",
              "format": "int32"
            }
          }
        ],
        "requestBody": {
          "content": {
            "application/json": {
              "schema": {
                "$ref": "#/components/schemas/EventDto"
              }
            },
            "text/json": {
              "schema": {
                "$ref": "#/components/schemas/EventDto"
              }
            },
            "application/*+json": {
              "schema": {
                "$ref": "#/components/schemas/EventDto"
              }
            }
          }
        },
        "responses": {
          "200": {
            "description": "OK"
          }
        }
      },
      "delete": {
        "tags": [
          "Events"
        ],
        "parameters": [
          {
            "name": "id",
            "in": "path",
            "required": true,
            "schema": {
              "type": "integer",
              "format": "int32"
            }
          }
        ],
        "responses": {
          "200": {
            "description": "OK"
          }
        }
      }
    },
    "/api/Events/type/{eventTypeId}": {
      "get": {
        "tags": [
          "Events"
        ],
        "parameters": [
          {
            "name": "eventTypeId",
            "in": "path",
            "required": true,
            "schema": {
              "type": "integer",
              "format": "int32"
            }
          }
        ],
        "responses": {
          "200": {
            "description": "OK"
          }
        }
      }
    },
    "/api/Events/search/{eventTitle}": {
      "get": {
        "tags": [
          "Events"
        ],
        "parameters": [
          {
            "name": "eventTitle",
            "in": "path",
            "required": true,
            "schema": {
              "type": "string"
            }
          }
        ],
        "responses": {
          "200": {
            "description": "OK"
          }
        }
      }
    },
    "/api/EventType": {
      "get": {
        "tags": [
          "EventType"
        ],
        "responses": {
          "200": {
            "description": "OK"
          }
        }
      },
      "post": {
        "tags": [
          "EventType"
        ],
        "requestBody": {
          "content": {
            "application/json": {
              "schema": {
                "$ref": "#/components/schemas/EventTypeDto"
              }
            },
            "text/json": {
              "schema": {
                "$ref": "#/components/schemas/EventTypeDto"
              }
            },
            "application/*+json": {
              "schema": {
                "$ref": "#/components/schemas/EventTypeDto"
              }
            }
          }
        },
        "responses": {
          "200": {
            "description": "OK"
          }
        }
      }
    },
    "/api/EventType/{id}": {
      "put": {
        "tags": [
          "EventType"
        ],
        "parameters": [
          {
            "name": "id",
            "in": "path",
            "required": true,
            "schema": {
              "type": "integer",
              "format": "int32"
            }
          }
        ],
        "requestBody": {
          "content": {
            "application/json": {
              "schema": {
                "$ref": "#/components/schemas/EventType"
              }
            },
            "text/json": {
              "schema": {
                "$ref": "#/components/schemas/EventType"
              }
            },
            "application/*+json": {
              "schema": {
                "$ref": "#/components/schemas/EventType"
              }
            }
          }
        },
        "responses": {
          "200": {
            "description": "OK"
          }
        }
      },
      "delete": {
        "tags": [
          "EventType"
        ],
        "parameters": [
          {
            "name": "id",
            "in": "path",
            "required": true,
            "schema": {
              "type": "integer",
              "format": "int32"
            }
          }
        ],
        "responses": {
          "200": {
            "description": "OK"
          }
        }
      }
    },
    "/api/EventType/search/{name}": {
      "get": {
        "tags": [
          "EventType"
        ],
        "parameters": [
          {
            "name": "name",
            "in": "path",
            "required": true,
            "schema": {
              "type": "string"
            }
          }
        ],
        "responses": {
          "200": {
            "description": "OK"
          }
        }
      }
    },
    "/api/Location": {
      "get": {
        "tags": [
          "Location"
        ],
        "responses": {
          "200": {
            "description": "OK"
          }
        }
      },
      "post": {
        "tags": [
          "Location"
        ],
        "requestBody": {
          "content": {
            "application/json": {
              "schema": {
                "$ref": "#/components/schemas/LocationDto"
              }
            },
            "text/json": {
              "schema": {
                "$ref": "#/components/schemas/LocationDto"
              }
            },
            "application/*+json": {
              "schema": {
                "$ref": "#/components/schemas/LocationDto"
              }
            }
          }
        },
        "responses": {
          "200": {
            "description": "OK"
          }
        }
      }
    },
    "/api/Location/{id}": {
      "get": {
        "tags": [
          "Location"
        ],
        "parameters": [
          {
            "name": "id",
            "in": "path",
            "required": true,
            "schema": {
              "type": "integer",
              "format": "int32"
            }
          }
        ],
        "responses": {
          "200": {
            "description": "OK"
          }
        }
      },
      "put": {
        "tags": [
          "Location"
        ],
        "parameters": [
          {
            "name": "id",
            "in": "path",
            "required": true,
            "schema": {
              "type": "integer",
              "format": "int32"
            }
          }
        ],
        "requestBody": {
          "content": {
            "application/json": {
              "schema": {
                "$ref": "#/components/schemas/LocationDto"
              }
            },
            "text/json": {
              "schema": {
                "$ref": "#/components/schemas/LocationDto"
              }
            },
            "application/*+json": {
              "schema": {
                "$ref": "#/components/schemas/LocationDto"
              }
            }
          }
        },
        "responses": {
          "200": {
            "description": "OK"
          }
        }
      },
      "delete": {
        "tags": [
          "Location"
        ],
        "parameters": [
          {
            "name": "id",
            "in": "path",
            "required": true,
            "schema": {
              "type": "integer",
              "format": "int32"
            }
          }
        ],
        "responses": {
          "200": {
            "description": "OK"
          }
        }
      }
    },
    "/api/Location/search/{name}": {
      "get": {
        "tags": [
          "Location"
        ],
        "parameters": [
          {
            "name": "name",
            "in": "path",
            "required": true,
            "schema": {
              "type": "string"
            }
          }
        ],
        "responses": {
          "200": {
            "description": "OK"
          }
        }
      }
    },
    "/api/Registration": {
      "get": {
        "tags": [
          "Registration"
        ],
        "responses": {
          "200": {
            "description": "OK"
          }
        }
      }
    },
    "/api/Registration/{userId}": {
      "get": {
        "tags": [
          "Registration"
        ],
        "parameters": [
          {
            "name": "userId",
            "in": "path",
            "required": true,
            "schema": {
              "type": "integer",
              "format": "int32"
            }
          }
        ],
        "responses": {
          "200": {
            "description": "OK"
          }
        }
      }
    },
    "/api/Registration/register/{eventId}/{userId}": {
      "post": {
        "tags": [
          "Registration"
        ],
        "parameters": [
          {
            "name": "eventId",
            "in": "path",
            "required": true,
            "schema": {
              "type": "integer",
              "format": "int32"
            }
          },
          {
            "name": "userId",
            "in": "path",
            "required": true,
            "schema": {
              "type": "integer",
              "format": "int32"
            }
          }
        ],
        "requestBody": {
          "content": {
            "application/json": {
              "schema": {
                "$ref": "#/components/schemas/RegistrationDto"
              }
            },
            "text/json": {
              "schema": {
                "$ref": "#/components/schemas/RegistrationDto"
              }
            },
            "application/*+json": {
              "schema": {
                "$ref": "#/components/schemas/RegistrationDto"
              }
            }
          }
        },
        "responses": {
          "200": {
            "description": "OK"
          }
        }
      }
    },
    "/api/Registration/{id}": {
      "put": {
        "tags": [
          "Registration"
        ],
        "parameters": [
          {
            "name": "id",
            "in": "path",
            "required": true,
            "schema": {
              "type": "integer",
              "format": "int32"
            }
          }
        ],
        "responses": {
          "200": {
            "description": "OK"
          }
        }
      },
      "delete": {
        "tags": [
          "Registration"
        ],
        "parameters": [
          {
            "name": "id",
            "in": "path",
            "required": true,
            "schema": {
              "type": "integer",
              "format": "int32"
            }
          }
        ],
        "responses": {
          "200": {
            "description": "OK"
          }
        }
      }
    },
    "/api/UserRole": {
      "get": {
        "tags": [
          "UserRole"
        ],
        "responses": {
          "200": {
            "description": "OK"
          }
        }
      },
      "post": {
        "tags": [
          "UserRole"
        ],
        "requestBody": {
          "content": {
            "application/json": {
              "schema": {
                "$ref": "#/components/schemas/UserRoleDto"
              }
            },
            "text/json": {
              "schema": {
                "$ref": "#/components/schemas/UserRoleDto"
              }
            },
            "application/*+json": {
              "schema": {
                "$ref": "#/components/schemas/UserRoleDto"
              }
            }
          }
        },
        "responses": {
          "200": {
            "description": "OK"
          }
        }
      }
    },
    "/api/UserRole/{id}": {
      "delete": {
        "tags": [
          "UserRole"
        ],
        "parameters": [
          {
            "name": "id",
            "in": "path",
            "required": true,
            "schema": {
              "type": "integer",
              "format": "int32"
            }
          }
        ],
        "responses": {
          "200": {
            "description": "OK"
          }
        }
      }
    },
    "/WeatherForecast": {
      "get": {
        "tags": [
          "WeatherForecast"
        ],
        "operationId": "GetWeatherForecast",
        "responses": {
          "200": {
            "description": "OK",
            "content": {
              "text/plain": {
                "schema": {
                  "type": "array",
                  "items": {
                    "$ref": "#/components/schemas/WeatherForecast"
                  }
                }
              },
              "application/json": {
                "schema": {
                  "type": "array",
                  "items": {
                    "$ref": "#/components/schemas/WeatherForecast"
                  }
                }
              },
              "text/json": {
                "schema": {
                  "type": "array",
                  "items": {
                    "$ref": "#/components/schemas/WeatherForecast"
                  }
                }
              }
            }
          }
        }
      }
    }
  },
  "components": {
    "schemas": {
      "EventDto": {
        "required": [
          "endDate",
          "eventTitle",
          "eventTypeId",
          "locationId",
          "organizerId",
          "startDate"
        ],
        "type": "object",
        "properties": {
          "eventTitle": {
            "maxLength": 200,
            "minLength": 1,
            "type": "string"
          },
          "eventTypeId": {
            "type": "integer",
            "format": "int32"
          },
          "description": {
            "maxLength": 500,
            "type": "string",
            "nullable": true
          },
          "startDate": {
            "type": "string",
            "format": "date-time"
          },
          "endDate": {
            "type": "string",
            "format": "date-time"
          },
          "organizerId": {
            "type": "integer",
            "format": "int32"
          },
          "locationId": {
            "type": "integer",
            "format": "int32"
          }
        },
        "additionalProperties": false
      },
      "EventType": {
        "required": [
          "typeName"
        ],
        "type": "object",
        "properties": {
          "typeId": {
            "type": "integer",
            "format": "int32"
          },
          "typeName": {
            "maxLength": 50,
            "minLength": 1,
            "type": "string"
          }
        },
        "additionalProperties": false
      },
      "EventTypeDto": {
        "required": [
          "typeName"
        ],
        "type": "object",
        "properties": {
          "typeName": {
            "maxLength": 50,
            "minLength": 1,
            "type": "string"
          }
        },
        "additionalProperties": false
      },
      "LocationDto": {
        "required": [
          "address",
          "capacity",
          "locationName"
        ],
        "type": "object",
        "properties": {
          "locationName": {
            "maxLength": 150,
            "minLength": 1,
            "type": "string"
          },
          "address": {
            "minLength": 1,
            "type": "string"
          },
          "capacity": {
            "type": "integer",
            "format": "int32"
          }
        },
        "additionalProperties": false
      },
      "RegistrationDto": {
        "required": [
          "attendeeId",
          "eventId"
        ],
        "type": "object",
        "properties": {
          "attendeeId": {
            "type": "integer",
            "format": "int32"
          },
          "eventId": {
            "type": "integer",
            "format": "int32"
          }
        },
        "additionalProperties": false
      },
      "UserDto": {
        "required": [
          "email",
          "passwordHash",
          "userName"
        ],
        "type": "object",
        "properties": {
          "userName": {
            "maxLength": 100,
            "minLength": 1,
            "type": "string"
          },
          "email": {
            "minLength": 1,
            "type": "string",
            "format": "email"
          },
          "passwordHash": {
            "minLength": 1,
            "type": "string"
          },
          "userRoleId": {
            "type": "integer",
            "format": "int32"
          }
        },
        "additionalProperties": false
      },
      "UserRoleDto": {
        "type": "object",
        "properties": {
          "roleName": {
            "type": "string",
            "nullable": true
          }
        },
        "additionalProperties": false
      },
      "WeatherForecast": {
        "type": "object",
        "properties": {
          "date": {
            "type": "string",
            "format": "date"
          },
          "temperatureC": {
            "type": "integer",
            "format": "int32"
          },
          "temperatureF": {
            "type": "integer",
            "format": "int32",
            "readOnly": true
          },
          "summary": {
            "type": "string",
            "nullable": true
          }
        },
        "additionalProperties": false
      }
    }
  }
}